[
  {
    "date": "2026-03-25-scout-brief",
    "title": "Scout Daily Intelligence Brief",
    "preview": "# Scout Daily Intelligence Brief **Date:** March 25, 2026   **For:** Fabio Adam / Unidreamity   **To...",
    "type": "memory"
  },
  {
    "date": "research-resources",
    "title": "Scout Research Resources",
    "preview": "# Scout Research Resources ## Curated Database for Investigation  ---  ## Education & EdTech  ### Pr...",
    "type": "memory"
  },
  {
    "date": "scout-training-log",
    "title": "Scout Training Log",
    "preview": "# Scout Training Log ## Daily Research Excellence Training  ---  ## Session: March 25, 2026 **Focus ...",
    "type": "memory"
  },
  {
    "date": "vision-training-2026-03-25",
    "title": "Vision Training Log - 2026-03-25",
    "preview": "# Vision Training Log - 2026-03-25 ## Daily Training Session: Academic Excellence Focus  ---  ## 1. ...",
    "type": "memory"
  },
  {
    "date": "scout-training-2026-03-24",
    "title": "SCOUT ELITE TRAINING REPORT",
    "preview": "# SCOUT ELITE TRAINING REPORT **Date:** Tuesday, March 24, 2026 **Session ID:** 66fd09e2-2b0c-4d07-9...",
    "type": "memory"
  }
]